MANIFEST.in
README.rst
README.txt
setup.py
bigbluebutton/__init__.py
bigbluebutton/__init__.py.bak
bigbluebutton/utils.py
bigbluebutton.egg-info/PKG-INFO
bigbluebutton.egg-info/SOURCES.txt
bigbluebutton.egg-info/dependency_links.txt
bigbluebutton.egg-info/requires.txt
bigbluebutton.egg-info/top_level.txt