Metadata-Version: 1.2
Name: bigbluebutton
Version: 0.6.0
Summary: Python API for bigbluebutton.
Home-page: https://hg.sr.ht/~dreimark/bigbluebutton-python-api
Author: Reimar Bauer
Author-email: rb.proj@gmail.com
Maintainer: Reimar Bauer
Maintainer-email: rb.proj@gmail.com
License: MIT
Keywords: bigbluebutton
Platform: UNKNOWN
